{
  "lighting_products": [
    {
      "series_name": "Nexus Series",
      "image_path": "images/products/Nexus Series (1).png",
      "images": [
        "images/products/Nexus Series (1).png",
        "images/products/Nexus Series (2).png",
        "images/products/Nexus Series (3).png",
        "images/products/Nexus Series (4).png"
      ],
      "specifications": {
        "item_code": "W1.CB15",
        "watt": "7W / 12W / 18W",
        "reflector_color": "AB / GB / RG / MW / SB",
        "body_color": "Golden / Silver / White",
        "beam_angle": "24° / 38°",
        "dimension": "63*63*43 / 80*80*44 / 94*84*51",
        "cutout": "55MM / 75MM / 85MM",
        "chip_size": "13.5*13.5*11 mm"
      }
    },
    {
      "series_name": "Platina Series",
      "image_path": "images/products/platina series (1).png",
      "images": [
        "images/products/platina series (1).png",
        "images/products/platina series (2).png",
        "images/products/platina series (3).png",
        "images/products/platina series (4).png"
      ],
      "specifications": {
        "items": [
          {
            "item_no": "PL-7W",
            "power": "7W",
            "size": "Φ65*H55 mm",
            "cut_out": "Φ60 mm",
            "body_color": "WHITE/BLACK",
            "beam_angle": "24°"
          },
          {
            "item_no": "PL-12W",
            "power": "12W",
            "size": "Φ80*H65 mm",
            "cut_out": "Φ75 mm",
            "body_color": "WHITE/BLACK",
            "beam_angle": "36°"
          },
          {
            "item_no": "PL-18W",
            "power": "18W",
            "size": "Φ95*H75 mm",
            "cut_out": "Φ90 mm",
            "body_color": "WHITE/BLACK",
            "beam_angle": "36°"
          }
        ]
      }
    },
    {
      "series_name": "Rainbow Series",
      "image_path": "images/products/rainbow series (1).png",
      "images": [
        "images/products/rainbow series (1).png",
        "images/products/rainbow series (2).png",
        "images/products/rainbow series (3).png",
        "images/products/rainbow series (4).png"
      ],
      "specifications": {
        "items": [
          {
            "item_no": "SL-3+3W-RD",
            "power": "3+3W",
            "size": "Φ105*H25 mm",
            "cut_out_size": "Φ90 mm",
            "pcb_1": "173*6 15D mm",
            "pcb_2": "208*6 30D mm"
          },
          {
            "item_no": "SL-6+3W-RD",
            "power": "6+3W",
            "size": "Φ145*H25 mm",
            "cut_out_size": "Φ120 mm",
            "pcb_1": "286*6 30D mm",
            "pcb_2": "321*6 30D mm"
          },
          {
            "item_no": "SL-12+4W-RD",
            "power": "12+4W",
            "size": "Φ195*H25 mm",
            "cut_out_size": "Φ160 mm",
            "pcb_1": "438*6 60D mm",
            "pcb_2": "471*6 40D mm"
          }
        ]
      }
    },
    {
      "series_name": "Vela Series",
      "image_path": "images/products/vela series (1).png",
      "images": [
        "images/products/vela series (1).png",
        "images/products/vela series (2).png"
      ],
      "specifications": {
        "items": [
          {
            "item_no": "VL-7W",
            "power": "7W",
            "size": "Φ70*H60 mm",
            "cut_out": "Φ65 mm",
            "body_color": "WHITE/BLACK",
            "beam_angle": "24°"
          },
          {
            "item_no": "VL-12W",
            "power": "12W",
            "size": "Φ85*H70 mm",
            "cut_out": "Φ80 mm",
            "body_color": "WHITE/BLACK",
            "beam_angle": "36°"
          },
          {
            "item_no": "VL-18W",
            "power": "18W",
            "size": "Φ100*H80 mm",
            "cut_out": "Φ95 mm",
            "body_color": "WHITE/BLACK",
            "beam_angle": "36°"
          }
        ]
      }
    }
  ]
}
